opler/__init__.py
opler-0.0.1.dist-info/WHEEL
opler-0.0.1.dist-info/entry_points.txt
opler-0.0.1.dist-info/METADATA
opler-0.0.1.dist-info/RECORD
